README.md
setup.py
Topsis_Ridhima_102017100.egg-info/PKG-INFO
Topsis_Ridhima_102017100.egg-info/SOURCES.txt
Topsis_Ridhima_102017100.egg-info/dependency_links.txt
Topsis_Ridhima_102017100.egg-info/entry_points.txt
Topsis_Ridhima_102017100.egg-info/requires.txt
Topsis_Ridhima_102017100.egg-info/top_level.txt
topsis/ridhima.py