Metadata-Version: 2.1
Name: Topsis-Ridhima-102017100
Version: 1.0.0.4
Summary: Python Library that perform TOPSIS
Home-page: UNKNOWN
Author: Ridhima Gupta
Author-email: 600ridhima@gmail.com
License: MIT
Platform: UNKNOWN
Classifier: License :: OSI Approved :: MIT License
Classifier: Programming Language :: Python :: 3.6
Classifier: Programming Language :: Python :: 3.7
Classifier: Programming Language :: Python :: 3.8
